diff_predictor/__init__.py
diff_predictor/aws_commands.py
diff_predictor/core.py
diff_predictor/data_process.py
diff_predictor/dataio.py
diff_predictor/eval.py
diff_predictor/pred_neural_net.py
diff_predictor/predxgboost 2.py
diff_predictor/predxgboost.py
diff_predictor/spatial.py
diff_predictor/temporal.py
diff_predictor/utils.py
diff_predictor/version.py
diff_predictor-1.0.2.dev0.dist-info/LICENSE
diff_predictor-1.0.2.dev0.dist-info/METADATA
diff_predictor-1.0.2.dev0.dist-info/WHEEL
diff_predictor-1.0.2.dev0.dist-info/top_level.txt
diff_predictor-1.0.2.dev0.dist-info/RECORD
