Metadata-Version: 2.1
Name: diff_predictor
Version: 1.0.2.dev0
Summary: diff_predictor: a prediciton package for multiple particle tracking data
Home-page: https://github.com/Nance-Lab/diff_predictor
Download-URL: 
Author: David Shackelford
Author-email: david.c.shackelford@gmail.com
Maintainer: Nels Schimek
Maintainer-email: nlsschim@uw.edu
License: MIT
Platform: OS Independent
Classifier: Development Status :: 3 - Alpha
Classifier: Environment :: Console
Classifier: Intended Audience :: Science/Research
Classifier: License :: OSI Approved :: MIT License
Classifier: Operating System :: OS Independent
Classifier: Programming Language :: Python
Classifier: Topic :: Scientific/Engineering
Requires-Python: >= 3.7.6
License-File: LICENSE
Requires-Dist: numpy ==1.21.6
Requires-Dist: scipy ==1.7.3
Requires-Dist: pandas ==1.3.2
Requires-Dist: matplotlib ==3.5.1
Requires-Dist: seaborn ==0.12.2
Requires-Dist: ipython ==7.34.0
Requires-Dist: ipykernel >=6.0.0
Requires-Dist: jupyter ==1.0.0
Requires-Dist: scikit-learn ==1.0.2
Requires-Dist: boto3 ==1.26.118
Requires-Dist: shapely ==2.0.1
Requires-Dist: shap ==0.41.0
Requires-Dist: xgboost ==1.2.1
Requires-Dist: hypothesis >=6.14.3
